sqlite2rest/__init__.py
sqlite2rest/__main__.py
sqlite2rest/app.py
sqlite2rest/database.py
sqlite2rest/openapi.py
sqlite2rest/routes.py
sqlite2rest-1.5.0.dist-info/LICENSE
sqlite2rest-1.5.0.dist-info/METADATA
sqlite2rest-1.5.0.dist-info/WHEEL
sqlite2rest-1.5.0.dist-info/entry_points.txt
sqlite2rest-1.5.0.dist-info/top_level.txt
sqlite2rest-1.5.0.dist-info/RECORD
