Metadata-Version: 2.1
Name: sqlite2rest
Version: 1.5.0
Summary: A Python library for creating a RESTful API from an SQLite database using Flask.
Home-page: https://github.com/nside/sqlite2rest
Author: Denis Laprise
Author-email: git@2ni.net
Classifier: Development Status :: 5 - Production/Stable
Classifier: Intended Audience :: Developers
Classifier: License :: OSI Approved :: MIT License
Classifier: Programming Language :: Python :: 3
Classifier: Programming Language :: Python :: 3.6
Classifier: Programming Language :: Python :: 3.7
Classifier: Programming Language :: Python :: 3.8
Classifier: Programming Language :: Python :: 3.9
Requires-Python: >=3.6
License-File: LICENSE
Requires-Dist: flask (==2.3.2)
Requires-Dist: openapi-spec-validator (==0.6.0)
Requires-Dist: pyyaml (==6.0.1)
